{
    "Summary XML documentation": {
        "prefix": "docsummary",
        "body": [
            "/// <summary>",
            "/// ${1:your description}",
            "/// </summary>"
        ],
        "description": "This snippet is creating the summary xml documentation."
    },
    "Example code XML documentation": {
        "prefix": "docexamplecode",
        "body": [
            "/// <example>",
            "/// ${1:example description}",
            "/// <code>",
            "/// ${2:example code}",
            "/// </code>",
            "/// </example>"
        ],
        "description": "This snippet is creating the example code section for xml documentation."
    },
    "Remarks XML documentation": {
        "prefix": "docremarks",
        "body": [
            "/// <remarks>",
            "/// ${1:remark description}",
            "/// </remarks>"
        ],
        "description": "This snippet is creating the remarks section for xml documentation."
    }
}